SFC_Jax/Fmodel.py
SFC_Jax/VERSION
SFC_Jax/__init__.py
SFC_Jax/mask.py
SFC_Jax/packingscore.py
SFC_Jax/symmetry.py
SFC_Jax/utils.py
SFC_Jax/voxel.py
tests/__init__.py
tests/conftest.py
tests/test_Fmodel.py
tests/test_voxel.py
SFcalculator_jax-0.1.5.dist-info/METADATA
SFcalculator_jax-0.1.5.dist-info/WHEEL
SFcalculator_jax-0.1.5.dist-info/top_level.txt
SFcalculator_jax-0.1.5.dist-info/RECORD
